{
    "data": {
        "@version": "3.0",
        "@time": "2024-07-19 09:05:09",
        "@type": "post",
        "@filename": "b000000011.xml",
        "open_time": "0000-00-00",
        "close_time": "0000-00-00",
        "lang_name": "Big5",
        "board_id": "1001162649",
        "node": "000000011",
        "site": "1000110001",
        "pt": "2022-10-14 00:42:04",
        "poster": "11027149",
        "realname": "游婕歆",
        "email": "xin090918@gmail.com",
        "homepage": null,
        "subject": "118. 令ptrX指向鏈結串列的節點，比較ptrX = ptrX-&gt;next和ptrX-&gt;next = ptrX的差異。",
        "content": "<p>ptrX=prtX-&gt;next;</p>\r\n\r\n<p>目前指標(ptrX)指向目前的下一筆資料。</p>\r\n\r\n<p>ptrX-&gt;next=ptrX;</p>\r\n\r\n<p>指標指向自己，如果指標會一直指向自己，可能會讓鏈結錯誤，跑迴圈時可能會遇到無窮迴圈。</p>",
        "attach": null,
        "rcount": null,
        "rank": null,
        "hit": "33",
        "lang": "1"
    }
}