{
    "data": {
        "@version": "3.0",
        "@time": "2024-07-19 08:49:45",
        "@type": "post",
        "@filename": "b000000013.xml",
        "open_time": "0000-00-00",
        "close_time": "0000-00-00",
        "lang_name": "Big5",
        "board_id": "1001305433",
        "node": "000000013",
        "site": "1000110001",
        "pt": "2023-10-15 07:07:30",
        "poster": "11127228",
        "realname": "周義庭",
        "email": "qaz20031211@gmail.com",
        "homepage": null,
        "subject": "120. 舉例說明使用雙向鏈結串列doubly linked list的情境。",
        "content": "<p>雙向鏈結串列（Doubly Linked List）是一種常見的數據結構，它與單向鏈結串列（Singly Linked List）不同，每個節點都包含指向前一個節點和後一個節點的鏈結。</p>\r\n\r\n<p>例如：</p>\r\n\r\n<p>瀏覽網頁的瀏覽器歷史記錄： 瀏覽器可以使用雙向鏈結串列來實現歷史記錄。每個節點代表一個訪問的網頁，並且有一個指向前一個訪問網頁和下一個訪問網頁的鏈結。這樣，用戶可以輕鬆地在網頁之間前進和後退，而無需重新加載。</p>\r\n\r\n<p>雙向鏈結串列的主要優勢是它允許在不需要重新遍歷整個串列的情況下，以常數時間訪問前一個節點，這對於某些應用非常有用。然而，它也需要更多的內存，因為每個節點需要存儲兩個鏈結指針。</p>",
        "attach": null,
        "rcount": null,
        "rank": null,
        "hit": "12",
        "lang": "1"
    }
}