{
    "data": {
        "@version": "3.0",
        "@time": "2024-07-19 08:54:22",
        "@type": "post",
        "@filename": "b000000008.xml",
        "open_time": "0000-00-00",
        "close_time": "0000-00-00",
        "lang_name": "Big5",
        "board_id": "1001296423",
        "node": "000000008",
        "site": "1000110001",
        "pt": "2023-11-29 11:47:14",
        "poster": "11127133",
        "realname": "陳乙菁",
        "email": "fiona99107@gmail.com",
        "homepage": null,
        "subject": "201",
        "content": "<p>201. 舉例說明單一佇列模擬如何計算平均等候時間waiting time。</p>\r\n\r\n<p>OID&nbsp;&nbsp; &nbsp;Arrival&nbsp;&nbsp; &nbsp;Duration&nbsp;&nbsp; &nbsp;TimeOut<br />\r\n101&nbsp;&nbsp; &nbsp;3&nbsp; &nbsp; 9&nbsp;&nbsp; &nbsp;12<br />\r\n112&nbsp;&nbsp; &nbsp;5&nbsp;&nbsp; &nbsp;6&nbsp;&nbsp; &nbsp;13<br />\r\n103&nbsp;&nbsp; &nbsp;6&nbsp;&nbsp; &nbsp;7&nbsp;&nbsp; &nbsp;15<br />\r\n106&nbsp;&nbsp; &nbsp;6&nbsp;&nbsp; &nbsp;9&nbsp;&nbsp; &nbsp;17<br />\r\n108&nbsp;&nbsp; &nbsp;6&nbsp;&nbsp; &nbsp;8&nbsp;&nbsp; &nbsp;18</p>\r\n\r\n<p>101 delay 0</p>\r\n\r\n<p>108 delay 0=(6-6)</p>\r\n\r\n<p>112 delay 8=(13-5)</p>\r\n\r\n<p>103 delay 9=(15-6)</p>\r\n\r\n<p>106 delay 11=(17-6)</p>\r\n\r\n<p>(0+0+8+9+11)/5 = 5.6</p>",
        "attach": null,
        "rcount": null,
        "rank": null,
        "hit": "13",
        "lang": "1"
    }
}